.gitignore
README
setup.py
nosmsd/__init__.py
nosmsd/admin.py
nosmsd/database.py
nosmsd/django_routers.py
nosmsd/handlers.py
nosmsd/models.py
nosmsd/nosmsd_incoming.py
nosmsd/nosmsd_inject.py
nosmsd/nosmsd_sendout.py
nosmsd/settings.py
nosmsd/smsd_errors.py
nosmsd/utils.py
nosmsd.egg-info/PKG-INFO
nosmsd.egg-info/SOURCES.txt
nosmsd.egg-info/dependency_links.txt
nosmsd.egg-info/not-zip-safe
nosmsd.egg-info/requires.txt
nosmsd.egg-info/top_level.txt
nosmsd/contrib/gammu-smsdrc
nosmsd/contrib/nosmsd-gammu-alter.sql
nosmsd/contrib/nosmsd-gammu-full.sql
nosmsd/contrib/nosmsd.conf.py
nosmsd/management/__init__.py
nosmsd/management/commands/__init__.py
nosmsd/management/commands/nosmsd_incoming.py
nosmsd/management/commands/nosmsd_inject.py
nosmsd/management/commands/nosmsd_sendout.py