Metadata-Version: 1.1
Name: nosmsd
Version: 0.26
Summary: Python wrapper around Gammu-smsd Database.
Home-page: http://github.com/yeleman/nosmsd
Author: yɛlɛman s.à.r.l
Author-email: reg@yeleman.com
License: GNU Lesser General Public License (LGPL), Version 3
Keywords: sms gammu smsd
Platform: UNKNOWN
Classifier: Development Status :: 4 - Beta
Classifier: Intended Audience :: Developers
Classifier: License :: OSI Approved :: MIT License
Classifier: Programming Language :: Python
Classifier: Programming Language :: SQL
Classifier: Operating System :: OS Independent
Provides: nosmsd
